{
    "umbrellaSummary": [
        {
            "UMBRELLANAME": "Avion Contracting",
            "CITY": null,
            "INITIALLYLICENSED": null,
            "OUTSTANDINGAMT": null,
            "OUTSTANDINGAMTTAB": null,
            "BREACH": null,
            "LOWRISE": null,
            "CHARGEABLECONCILIATION": 0,
            "TOTALUNITS": 0,
            "CONDOCOUNT": null,
            "TOTAL_CLAIMS": 0,
            "ADDRESS": "59 Glen Road",
            "TELEPHONE": "705-444-8553",
            "FAX": "705-444-8235",
            "WEBSITEURL": " ",
            "EMAIL": "avin-inc@rogers.com",
            "SUMM_FREEHOLD": 0,
            "SUMM_CONDO": 0,
            "SUMM_TOTAL": 0,
            "SUMM_CC": 0,
            "SUMM_MINOR": 0,
            "SUMM_MINOR_AMT": 0,
            "SUMM_MAJOR": 0,
            "SUMM_MAJOR_AMT": 0,
            "SUMM_TOTAL_CLAIMS": 0
        }
    ],
    "umbrellaMembers": [
        {
            "MEMBERNAME": "1035110 Ontario Inc.",
            "MEMBEROPERATINGNAME": "Avion Contracting",
            "MEMBERVBNUM": "B27928",
            "MEMBERLICENCESTATUS": "Expired"
        },
        {
            "MEMBERNAME": "1035110 Ontario Inc.",
            "MEMBEROPERATINGNAME": "Avion Contracting",
            "MEMBERVBNUM": "B39595",
            "MEMBERLICENCESTATUS": "Licensed"
        }
    ],
    "umbrellaProperties": [],
    "umbrellaCondoProjects": []
}