{
    "builderSummary": [
        {
            "Account Number": "B24802",
            "Umbrella": null,
            "Umbrella ID": null,
            "VB_NAME": "John Newman Contracting Inc.",
            "OPERATINGNAME": null,
            "CITY": "ENNISMORE",
            "HCRA_INITIALLICENSEDATE": "1995-05-30",
            "LICENCE_STATUS": "Expired",
            "HCRA_LICENSERENEWEDON": "2001-05-31 12:38:01.000 +0000",
            "Expiry Date": null,
            "RENL_IN_PROCESS_FLAG": "N",
            "ADDRESS": "435 Edenderry Line",
            "TELEPHONE": "(705)292-8957",
            "FAX": "(705)292-5898",
            "WEBSITEURL": null,
            "EMAIL": null,
            "ACCOUNTNUMBER": null,
            "Total Outstanding Amount": null,
            "TAB": null,
            "BREACH": null,
            "SUMM_FREEHOLD": 0,
            "SUMM_CONDO": 0,
            "SUMM_TOTAL": 0,
            "SUMM_CC": 0,
            "SUMM_MINOR": 0,
            "SUMM_MINOR_AMT": 0,
            "SUMM_MAJOR": 0,
            "SUMM_MAJOR_AMT": 0,
            "SUMM_TOTAL_CLAIMS": 0
        }
    ],
    "builderPDOs": [
        {
            "TOUNIQUENUMBER": "340764",
            "TO": "Charlene Rogers",
            "Relationship Type": "Officer",
            "STATUS": "Active",
            "PDO_CONTACT_INFO": "705-292-5185"
        },
        {
            "TOUNIQUENUMBER": "340763",
            "TO": "Lynn Louise Fawcett",
            "Relationship Type": "Officer",
            "STATUS": "Active",
            "PDO_CONTACT_INFO": "705-743-3747"
        },
        {
            "TOUNIQUENUMBER": "340763",
            "TO": "Lynn Louise Fawcett",
            "Relationship Type": "Director",
            "STATUS": "Active",
            "PDO_CONTACT_INFO": "705-743-3747"
        },
        {
            "TOUNIQUENUMBER": "340763",
            "TO": "Lynn Louise Fawcett",
            "Relationship Type": "Principal",
            "STATUS": "Active",
            "PDO_CONTACT_INFO": "705-743-3747"
        },
        {
            "TOUNIQUENUMBER": "340762",
            "TO": "Robert Fawcett",
            "Relationship Type": "Director",
            "STATUS": "Active",
            "PDO_CONTACT_INFO": "705-292-8957"
        },
        {
            "TOUNIQUENUMBER": "340762",
            "TO": "Robert Fawcett",
            "Relationship Type": "Officer",
            "STATUS": "Active",
            "PDO_CONTACT_INFO": "705-292-8957"
        },
        {
            "TOUNIQUENUMBER": "340762",
            "TO": "Robert Fawcett",
            "Relationship Type": "Principal",
            "STATUS": "Active",
            "PDO_CONTACT_INFO": "705-292-8957"
        }
    ],
    "builderConvictions": [],
    "builderMembers": [
        {
            "Account Number": "B24802",
            "Umbrella": null,
            "Umbrella ID": null,
            "VB_NAME": "John Newman Contracting Inc.",
            "OPERATINGNAME": null,
            "LICENCE_STATUS": "Expired",
            "MEMBERVBNUM": null,
            "MEMBERNAME": null,
            "MEMBEROPERATINGNAME": null,
            "MEMBERLICENCESTATUS": null
        }
    ],
    "builderCondoProjects": [],
    "builderConditions": []
}