{
    "builderSummary": [
        {
            "Account Number": "B285",
            "Umbrella": null,
            "Umbrella ID": null,
            "VB_NAME": "Capri Realties Ltd.",
            "OPERATINGNAME": null,
            "CITY": "L'ORIGNAL",
            "HCRA_INITIALLICENSEDATE": "1977-08-08",
            "LICENCE_STATUS": "Expired",
            "HCRA_LICENSERENEWEDON": "1982-10-22 09:59:58.000 +0000",
            "Expiry Date": null,
            "RENL_IN_PROCESS_FLAG": "N",
            "ADDRESS": "392 Front St",
            "TELEPHONE": "(807)473-9383",
            "FAX": null,
            "WEBSITEURL": null,
            "EMAIL": null,
            "ACCOUNTNUMBER": null,
            "Total Outstanding Amount": null,
            "TAB": null,
            "BREACH": null,
            "SUMM_FREEHOLD": 0,
            "SUMM_CONDO": 0,
            "SUMM_TOTAL": 0,
            "SUMM_CC": 0,
            "SUMM_MINOR": 0,
            "SUMM_MINOR_AMT": 0,
            "SUMM_MAJOR": 0,
            "SUMM_MAJOR_AMT": 0,
            "SUMM_TOTAL_CLAIMS": 0
        }
    ],
    "builderPDOs": [
        {
            "TOUNIQUENUMBER": "333414",
            "TO": "Germain Tessier",
            "Relationship Type": "Principal",
            "STATUS": "Active",
            "PDO_CONTACT_INFO": null
        },
        {
            "TOUNIQUENUMBER": "333419",
            "TO": "Yolande Tessier",
            "Relationship Type": "Principal",
            "STATUS": "Active",
            "PDO_CONTACT_INFO": null
        }
    ],
    "builderConvictions": [],
    "builderMembers": [
        {
            "Account Number": "B285",
            "Umbrella": null,
            "Umbrella ID": null,
            "VB_NAME": "Capri Realties Ltd.",
            "OPERATINGNAME": null,
            "LICENCE_STATUS": "Expired",
            "MEMBERVBNUM": null,
            "MEMBERNAME": null,
            "MEMBEROPERATINGNAME": null,
            "MEMBERLICENCESTATUS": null
        }
    ],
    "builderCondoProjects": [],
    "builderConditions": []
}