{
    "builderSummary": [
        {
            "Account Number": "B30772",
            "Umbrella": "Davies Smith Developments",
            "Umbrella ID": "11762897",
            "VB_NAME": "2077 Lakeshore Blvd. W. Ltd.",
            "OPERATINGNAME": "Grenadier Landing",
            "CITY": "Mississauga",
            "HCRA_INITIALLICENSEDATE": "2000-06-07",
            "LICENCE_STATUS": "Expired",
            "HCRA_LICENSERENEWEDON": "2005-06-08 12:30:54.000 +0000",
            "Expiry Date": null,
            "RENL_IN_PROCESS_FLAG": "N",
            "ADDRESS": "P.O. Box 53003 Erin Mills",
            "TELEPHONE": "(416) 363-1030 ext. 225",
            "FAX": "(416) 363-1258",
            "WEBSITEURL": "www.grenadier-landing.com",
            "EMAIL": "info@davies.smith.com",
            "ACCOUNTNUMBER": null,
            "Total Outstanding Amount": null,
            "TAB": null,
            "BREACH": null,
            "SUMM_FREEHOLD": 0,
            "SUMM_CONDO": 0,
            "SUMM_TOTAL": 0,
            "SUMM_CC": 0,
            "SUMM_MINOR": 0,
            "SUMM_MINOR_AMT": 0,
            "SUMM_MAJOR": 0,
            "SUMM_MAJOR_AMT": 0,
            "SUMM_TOTAL_CLAIMS": 0
        }
    ],
    "builderPDOs": [
        {
            "TOUNIQUENUMBER": "342249",
            "TO": "Walter Davies",
            "Relationship Type": "Officer",
            "STATUS": "Active",
            "PDO_CONTACT_INFO": null
        },
        {
            "TOUNIQUENUMBER": "342249",
            "TO": "Walter Davies",
            "Relationship Type": "Director",
            "STATUS": "Active",
            "PDO_CONTACT_INFO": null
        },
        {
            "TOUNIQUENUMBER": "12399376",
            "TO": "Jessica Stachiw",
            "Relationship Type": "Sales & Marketing Contact",
            "STATUS": "Active",
            "PDO_CONTACT_INFO": "416-363-1030 Ext-227"
        },
        {
            "TOUNIQUENUMBER": "342251",
            "TO": "Ian Smith",
            "Relationship Type": "Director",
            "STATUS": "Active",
            "PDO_CONTACT_INFO": null
        },
        {
            "TOUNIQUENUMBER": "342251",
            "TO": "Ian Smith",
            "Relationship Type": "Officer",
            "STATUS": "Active",
            "PDO_CONTACT_INFO": null
        }
    ],
    "builderConvictions": [],
    "builderMembers": [
        {
            "Account Number": "B30772",
            "Umbrella": "Davies Smith Developments",
            "Umbrella ID": "11762897",
            "VB_NAME": "2077 Lakeshore Blvd. W. Ltd.",
            "OPERATINGNAME": "Grenadier Landing",
            "LICENCE_STATUS": "Expired",
            "MEMBERVBNUM": "B36010",
            "MEMBERNAME": "Marine Parade Drive Limited",
            "MEMBEROPERATINGNAME": "Hearthstone",
            "MEMBERLICENCESTATUS": "Expired"
        },
        {
            "Account Number": "B30772",
            "Umbrella": "Davies Smith Developments",
            "Umbrella ID": "11762897",
            "VB_NAME": "2077 Lakeshore Blvd. W. Ltd.",
            "OPERATINGNAME": "Grenadier Landing",
            "LICENCE_STATUS": "Expired",
            "MEMBERVBNUM": "B30772",
            "MEMBERNAME": "2077 Lakeshore Blvd. W. Ltd.",
            "MEMBEROPERATINGNAME": "Grenadier Landing",
            "MEMBERLICENCESTATUS": "Expired"
        },
        {
            "Account Number": "B30772",
            "Umbrella": "Davies Smith Developments",
            "Umbrella ID": "11762897",
            "VB_NAME": "2077 Lakeshore Blvd. W. Ltd.",
            "OPERATINGNAME": "Grenadier Landing",
            "LICENCE_STATUS": "Expired",
            "MEMBERVBNUM": "B37030",
            "MEMBERNAME": "Solstice Two Limited",
            "MEMBEROPERATINGNAME": "Onyx",
            "MEMBERLICENCESTATUS": "Expired"
        },
        {
            "Account Number": "B30772",
            "Umbrella": "Davies Smith Developments",
            "Umbrella ID": "11762897",
            "VB_NAME": "2077 Lakeshore Blvd. W. Ltd.",
            "OPERATINGNAME": "Grenadier Landing",
            "LICENCE_STATUS": "Expired",
            "MEMBERVBNUM": "B32076",
            "MEMBERNAME": "Citygate One Ltd.",
            "MEMBEROPERATINGNAME": "City Gate",
            "MEMBERLICENCESTATUS": "Expired"
        },
        {
            "Account Number": "B30772",
            "Umbrella": "Davies Smith Developments",
            "Umbrella ID": "11762897",
            "VB_NAME": "2077 Lakeshore Blvd. W. Ltd.",
            "OPERATINGNAME": "Grenadier Landing",
            "LICENCE_STATUS": "Expired",
            "MEMBERVBNUM": "B38531",
            "MEMBERNAME": "Appleby Burlington Limited",
            "MEMBEROPERATINGNAME": "Ironstone",
            "MEMBERLICENCESTATUS": "Expired"
        },
        {
            "Account Number": "B30772",
            "Umbrella": "Davies Smith Developments",
            "Umbrella ID": "11762897",
            "VB_NAME": "2077 Lakeshore Blvd. W. Ltd.",
            "OPERATINGNAME": "Grenadier Landing",
            "LICENCE_STATUS": "Expired",
            "MEMBERVBNUM": "B33240",
            "MEMBERNAME": "Citygate Two Ltd.",
            "MEMBEROPERATINGNAME": "Citygate",
            "MEMBERLICENCESTATUS": "Expired"
        },
        {
            "Account Number": "B30772",
            "Umbrella": "Davies Smith Developments",
            "Umbrella ID": "11762897",
            "VB_NAME": "2077 Lakeshore Blvd. W. Ltd.",
            "OPERATINGNAME": "Grenadier Landing",
            "LICENCE_STATUS": "Expired",
            "MEMBERVBNUM": "B36545",
            "MEMBERNAME": "Victoria Charles Inc.",
            "MEMBEROPERATINGNAME": "The Rowe",
            "MEMBERLICENCESTATUS": "Expired"
        },
        {
            "Account Number": "B30772",
            "Umbrella": "Davies Smith Developments",
            "Umbrella ID": "11762897",
            "VB_NAME": "2077 Lakeshore Blvd. W. Ltd.",
            "OPERATINGNAME": "Grenadier Landing",
            "LICENCE_STATUS": "Expired",
            "MEMBERVBNUM": "B33488",
            "MEMBERNAME": "Davies Smith Developments Partnership",
            "MEMBEROPERATINGNAME": null,
            "MEMBERLICENCESTATUS": "Expired"
        },
        {
            "Account Number": "B30772",
            "Umbrella": "Davies Smith Developments",
            "Umbrella ID": "11762897",
            "VB_NAME": "2077 Lakeshore Blvd. W. Ltd.",
            "OPERATINGNAME": "Grenadier Landing",
            "LICENCE_STATUS": "Expired",
            "MEMBERVBNUM": "B40793",
            "MEMBERNAME": "Eleven Superior Ltd.",
            "MEMBEROPERATINGNAME": null,
            "MEMBERLICENCESTATUS": "Expired"
        },
        {
            "Account Number": "B30772",
            "Umbrella": "Davies Smith Developments",
            "Umbrella ID": "11762897",
            "VB_NAME": "2077 Lakeshore Blvd. W. Ltd.",
            "OPERATINGNAME": "Grenadier Landing",
            "LICENCE_STATUS": "Expired",
            "MEMBERVBNUM": "B25956",
            "MEMBERNAME": "Davies Smith Developments Inc.",
            "MEMBEROPERATINGNAME": "Davies, Master Builder",
            "MEMBERLICENCESTATUS": "Expired"
        },
        {
            "Account Number": "B30772",
            "Umbrella": "Davies Smith Developments",
            "Umbrella ID": "11762897",
            "VB_NAME": "2077 Lakeshore Blvd. W. Ltd.",
            "OPERATINGNAME": "Grenadier Landing",
            "LICENCE_STATUS": "Expired",
            "MEMBERVBNUM": "B35423",
            "MEMBERNAME": "Solstice One Limited",
            "MEMBEROPERATINGNAME": "Solstice",
            "MEMBERLICENCESTATUS": "Expired"
        }
    ],
    "builderCondoProjects": [],
    "builderConditions": []
}