{
    "builderSummary": [
        {
            "Account Number": "B31563",
            "Umbrella": null,
            "Umbrella ID": null,
            "VB_NAME": "Wendell's Renovations Inc..",
            "OPERATINGNAME": "Wendell's Renovations",
            "CITY": "TROY",
            "HCRA_INITIALLICENSEDATE": "2001-05-16",
            "LICENCE_STATUS": "Expired",
            "HCRA_LICENSERENEWEDON": "2009-05-17 15:00:41.000 +0000",
            "Expiry Date": null,
            "RENL_IN_PROCESS_FLAG": "N",
            "ADDRESS": "492 Orkney Rd, R.R.#1",
            "TELEPHONE": "(905)627-2369",
            "FAX": "(905)627-2369",
            "WEBSITEURL": null,
            "EMAIL": "kathywendellsren@aol.com",
            "ACCOUNTNUMBER": null,
            "Total Outstanding Amount": null,
            "TAB": null,
            "BREACH": null,
            "SUMM_FREEHOLD": 0,
            "SUMM_CONDO": 0,
            "SUMM_TOTAL": 0,
            "SUMM_CC": 0,
            "SUMM_MINOR": 0,
            "SUMM_MINOR_AMT": 0,
            "SUMM_MAJOR": 0,
            "SUMM_MAJOR_AMT": 0,
            "SUMM_TOTAL_CLAIMS": 0
        }
    ],
    "builderPDOs": [
        {
            "TOUNIQUENUMBER": "11709736",
            "TO": "Wendell Thompson",
            "Relationship Type": "Principal",
            "STATUS": "Active",
            "PDO_CONTACT_INFO": "905-570-9234"
        },
        {
            "TOUNIQUENUMBER": "11709737",
            "TO": "Katheryn Elizabeth Thompson",
            "Relationship Type": "Principal",
            "STATUS": "Active",
            "PDO_CONTACT_INFO": "905-531-7543"
        },
        {
            "TOUNIQUENUMBER": "11709737",
            "TO": "Katheryn Elizabeth Thompson",
            "Relationship Type": "Officer",
            "STATUS": "Active",
            "PDO_CONTACT_INFO": "905-531-7543"
        }
    ],
    "builderConvictions": [],
    "builderMembers": [
        {
            "Account Number": "B31563",
            "Umbrella": null,
            "Umbrella ID": null,
            "VB_NAME": "Wendell's Renovations Inc..",
            "OPERATINGNAME": "Wendell's Renovations",
            "LICENCE_STATUS": "Expired",
            "MEMBERVBNUM": null,
            "MEMBERNAME": null,
            "MEMBEROPERATINGNAME": null,
            "MEMBERLICENCESTATUS": null
        }
    ],
    "builderCondoProjects": [],
    "builderConditions": []
}