{
    "builderSummary": [
        {
            "Account Number": "B36412",
            "Umbrella": null,
            "Umbrella ID": null,
            "VB_NAME": "1245751 Ontario Inc.",
            "OPERATINGNAME": "Solid Homes Contracting",
            "CITY": "TORONTO",
            "HCRA_INITIALLICENSEDATE": "2006-03-20",
            "LICENCE_STATUS": "Expired",
            "HCRA_LICENSERENEWEDON": "2021-08-18 04:15:15.000 +0000",
            "Expiry Date": "2021-08-18",
            "RENL_IN_PROCESS_FLAG": "N",
            "ADDRESS": "123 Eglinton Ave. E.,  Unit 710",
            "TELEPHONE": "416-835-8239",
            "FAX": null,
            "WEBSITEURL": " ",
            "EMAIL": "zeki@solidhomes.ca",
            "ACCOUNTNUMBER": null,
            "Total Outstanding Amount": null,
            "TAB": null,
            "BREACH": null,
            "SUMM_FREEHOLD": 2,
            "SUMM_CONDO": 0,
            "SUMM_TOTAL": 2,
            "SUMM_CC": 0,
            "SUMM_MINOR": 0,
            "SUMM_MINOR_AMT": 0,
            "SUMM_MAJOR": 0,
            "SUMM_MAJOR_AMT": 0,
            "SUMM_TOTAL_CLAIMS": 0
        }
    ],
    "builderPDOs": [
        {
            "TOUNIQUENUMBER": "12139072",
            "TO": "Salih Zeki Kilic",
            "Relationship Type": "Principal",
            "STATUS": "Active",
            "PDO_CONTACT_INFO": "416-835-8239"
        },
        {
            "TOUNIQUENUMBER": "12139072",
            "TO": "Salih Zeki Kilic",
            "Relationship Type": "Officer",
            "STATUS": "Active",
            "PDO_CONTACT_INFO": "416-835-8239"
        },
        {
            "TOUNIQUENUMBER": "12139072",
            "TO": "Salih Zeki Kilic",
            "Relationship Type": "Director",
            "STATUS": "Active",
            "PDO_CONTACT_INFO": "416-835-8239"
        }
    ],
    "builderConvictions": [],
    "builderMembers": [
        {
            "Account Number": "B36412",
            "Umbrella": null,
            "Umbrella ID": null,
            "VB_NAME": "1245751 Ontario Inc.",
            "OPERATINGNAME": "Solid Homes Contracting",
            "LICENCE_STATUS": "Expired",
            "MEMBERVBNUM": null,
            "MEMBERNAME": null,
            "MEMBEROPERATINGNAME": null,
            "MEMBERLICENCESTATUS": null
        }
    ],
    "builderCondoProjects": [],
    "builderConditions": []
}