{
    "builderSummary": [
        {
            "Account Number": "B39059",
            "Umbrella": null,
            "Umbrella ID": null,
            "VB_NAME": "Lemar Custom Homes Limited",
            "OPERATINGNAME": null,
            "CITY": "MERRICKVILLE",
            "HCRA_INITIALLICENSEDATE": "2008-09-17",
            "LICENCE_STATUS": "Expired",
            "HCRA_LICENSERENEWEDON": "2010-09-18 15:01:35.000 +0000",
            "Expiry Date": null,
            "RENL_IN_PROCESS_FLAG": "N",
            "ADDRESS": "1171 Pioneer Rd.",
            "TELEPHONE": "613-269-3425",
            "FAX": "613-269-7986",
            "WEBSITEURL": null,
            "EMAIL": "ldhale@ripnet.com",
            "ACCOUNTNUMBER": null,
            "Total Outstanding Amount": null,
            "TAB": null,
            "BREACH": null,
            "SUMM_FREEHOLD": 0,
            "SUMM_CONDO": 0,
            "SUMM_TOTAL": 0,
            "SUMM_CC": 0,
            "SUMM_MINOR": 0,
            "SUMM_MINOR_AMT": 0,
            "SUMM_MAJOR": 0,
            "SUMM_MAJOR_AMT": 0,
            "SUMM_TOTAL_CLAIMS": 0
        }
    ],
    "builderPDOs": [
        {
            "TOUNIQUENUMBER": "11652858",
            "TO": "Sheldon Hale",
            "Relationship Type": "Director",
            "STATUS": "Active",
            "PDO_CONTACT_INFO": "613-269-3425"
        },
        {
            "TOUNIQUENUMBER": "11652858",
            "TO": "Sheldon Hale",
            "Relationship Type": "Officer",
            "STATUS": "Active",
            "PDO_CONTACT_INFO": "613-269-3425"
        },
        {
            "TOUNIQUENUMBER": "11652858",
            "TO": "Sheldon Hale",
            "Relationship Type": "Principal",
            "STATUS": "Active",
            "PDO_CONTACT_INFO": "613-269-3425"
        },
        {
            "TOUNIQUENUMBER": "12305515",
            "TO": "Michael Brazeau",
            "Relationship Type": "Director",
            "STATUS": "Active",
            "PDO_CONTACT_INFO": "613-269-4633"
        },
        {
            "TOUNIQUENUMBER": "12305515",
            "TO": "Michael Brazeau",
            "Relationship Type": "Principal",
            "STATUS": "Active",
            "PDO_CONTACT_INFO": "613-269-4633"
        }
    ],
    "builderConvictions": [],
    "builderMembers": [
        {
            "Account Number": "B39059",
            "Umbrella": null,
            "Umbrella ID": null,
            "VB_NAME": "Lemar Custom Homes Limited",
            "OPERATINGNAME": null,
            "LICENCE_STATUS": "Expired",
            "MEMBERVBNUM": null,
            "MEMBERNAME": null,
            "MEMBEROPERATINGNAME": null,
            "MEMBERLICENCESTATUS": null
        }
    ],
    "builderCondoProjects": [],
    "builderConditions": []
}