{
    "builderSummary": [
        {
            "Account Number": "B42244",
            "Umbrella": null,
            "Umbrella ID": null,
            "VB_NAME": "TJP Design Build Inc.",
            "OPERATINGNAME": null,
            "CITY": "London",
            "HCRA_INITIALLICENSEDATE": "2012-08-30",
            "LICENCE_STATUS": "Expired",
            "HCRA_LICENSERENEWEDON": "2015-08-31 19:35:36.000 +0000",
            "Expiry Date": null,
            "RENL_IN_PROCESS_FLAG": "N",
            "ADDRESS": "19-410 Ambleside Dr.",
            "TELEPHONE": "519/670-3359",
            "FAX": null,
            "WEBSITEURL": " ",
            "EMAIL": "braddunbar@me.com",
            "ACCOUNTNUMBER": "B42244",
            "Total Outstanding Amount": 18206.82,
            "TAB": 0,
            "BREACH": 18206.82,
            "SUMM_FREEHOLD": 6,
            "SUMM_CONDO": 0,
            "SUMM_TOTAL": 6,
            "SUMM_CC": 12,
            "SUMM_MINOR": 6,
            "SUMM_MINOR_AMT": 189435.18,
            "SUMM_MAJOR": 1,
            "SUMM_MAJOR_AMT": 12905,
            "SUMM_TOTAL_CLAIMS": 202340.18
        }
    ],
    "builderPDOs": [
        {
            "TOUNIQUENUMBER": "11707867",
            "TO": "Brad Dunbar",
            "Relationship Type": "Director",
            "STATUS": "Active",
            "PDO_CONTACT_INFO": "519-670-3359"
        },
        {
            "TOUNIQUENUMBER": "11707867",
            "TO": "Brad Dunbar",
            "Relationship Type": "Officer",
            "STATUS": "Active",
            "PDO_CONTACT_INFO": "519-670-3359"
        },
        {
            "TOUNIQUENUMBER": "100127201",
            "TO": "Jinx Dunbar",
            "Relationship Type": "Director",
            "STATUS": "Active",
            "PDO_CONTACT_INFO": "519-646-3942"
        }
    ],
    "builderConvictions": [],
    "builderMembers": [
        {
            "Account Number": "B42244",
            "Umbrella": null,
            "Umbrella ID": null,
            "VB_NAME": "TJP Design Build Inc.",
            "OPERATINGNAME": null,
            "LICENCE_STATUS": "Expired",
            "MEMBERVBNUM": null,
            "MEMBERNAME": null,
            "MEMBEROPERATINGNAME": null,
            "MEMBERLICENCESTATUS": null
        }
    ],
    "builderCondoProjects": [],
    "builderConditions": []
}