{
    "builderSummary": [
        {
            "Account Number": "B47229",
            "Umbrella": "Cade Custom Homes",
            "Umbrella ID": "12548871",
            "VB_NAME": "2519519 Ontario Inc.",
            "OPERATINGNAME": null,
            "CITY": "WHITBY",
            "HCRA_INITIALLICENSEDATE": "2018-08-31",
            "LICENCE_STATUS": "Expired",
            "HCRA_LICENSERENEWEDON": "2020-10-27 13:22:22.000 +0000",
            "Expiry Date": null,
            "RENL_IN_PROCESS_FLAG": "N",
            "ADDRESS": "40 Calder Cres",
            "TELEPHONE": "289/987-7020",
            "FAX": null,
            "WEBSITEURL": " ",
            "EMAIL": "cadecustomhomes@gmail.com",
            "ACCOUNTNUMBER": null,
            "Total Outstanding Amount": null,
            "TAB": null,
            "BREACH": null,
            "SUMM_FREEHOLD": 1,
            "SUMM_CONDO": 0,
            "SUMM_TOTAL": 1,
            "SUMM_CC": 0,
            "SUMM_MINOR": 0,
            "SUMM_MINOR_AMT": 0,
            "SUMM_MAJOR": 0,
            "SUMM_MAJOR_AMT": 0,
            "SUMM_TOTAL_CLAIMS": 0
        }
    ],
    "builderPDOs": [
        {
            "TOUNIQUENUMBER": "100316249",
            "TO": "Cade McMannis",
            "Relationship Type": "Officer",
            "STATUS": "Active",
            "PDO_CONTACT_INFO": "289-987-7020"
        },
        {
            "TOUNIQUENUMBER": "100316249",
            "TO": "Cade McMannis",
            "Relationship Type": "Director",
            "STATUS": "Active",
            "PDO_CONTACT_INFO": "289-987-7020"
        },
        {
            "TOUNIQUENUMBER": "100316249",
            "TO": "Cade McMannis",
            "Relationship Type": "Principal",
            "STATUS": "Active",
            "PDO_CONTACT_INFO": "289-987-7020"
        },
        {
            "TOUNIQUENUMBER": "100521430",
            "TO": "Stephanie McMannis",
            "Relationship Type": "Principal",
            "STATUS": "Active",
            "PDO_CONTACT_INFO": "289-987-7010"
        }
    ],
    "builderConvictions": [],
    "builderMembers": [
        {
            "Account Number": "B47229",
            "Umbrella": "Cade Custom Homes",
            "Umbrella ID": "12548871",
            "VB_NAME": "2519519 Ontario Inc.",
            "OPERATINGNAME": null,
            "LICENCE_STATUS": "Expired",
            "MEMBERVBNUM": "B47229",
            "MEMBERNAME": "2519519 Ontario Inc.",
            "MEMBEROPERATINGNAME": null,
            "MEMBERLICENCESTATUS": "Expired"
        },
        {
            "Account Number": "B47229",
            "Umbrella": "Cade Custom Homes",
            "Umbrella ID": "12548871",
            "VB_NAME": "2519519 Ontario Inc.",
            "OPERATINGNAME": null,
            "LICENCE_STATUS": "Expired",
            "MEMBERVBNUM": "B44687",
            "MEMBERNAME": "Cade McMannis",
            "MEMBEROPERATINGNAME": null,
            "MEMBERLICENCESTATUS": "Expired"
        }
    ],
    "builderCondoProjects": [],
    "builderConditions": []
}