{
    "builderSummary": [
        {
            "Account Number": "B47740",
            "Umbrella": null,
            "Umbrella ID": null,
            "VB_NAME": "Brighteast Inc.",
            "OPERATINGNAME": "Brighteast Construction",
            "CITY": "Fort Erie",
            "HCRA_INITIALLICENSEDATE": "2019-09-30",
            "LICENCE_STATUS": "Licensed",
            "HCRA_LICENSERENEWEDON": "2023-08-04 02:46:25.000 +0000",
            "Expiry Date": "2024-10-01",
            "RENL_IN_PROCESS_FLAG": "N",
            "ADDRESS": "1469 Sunset Drive",
            "TELEPHONE": "905-324-5588",
            "FAX": null,
            "WEBSITEURL": "www.brighteast.ca",
            "EMAIL": "kenny@brighteast.ca",
            "ACCOUNTNUMBER": null,
            "Total Outstanding Amount": null,
            "TAB": null,
            "BREACH": null,
            "SUMM_FREEHOLD": 0,
            "SUMM_CONDO": 0,
            "SUMM_TOTAL": 0,
            "SUMM_CC": 0,
            "SUMM_MINOR": 0,
            "SUMM_MINOR_AMT": 0,
            "SUMM_MAJOR": 0,
            "SUMM_MAJOR_AMT": 0,
            "SUMM_TOTAL_CLAIMS": 0
        }
    ],
    "builderPDOs": [
        {
            "TOUNIQUENUMBER": "100576388",
            "TO": "Ye Yu",
            "Relationship Type": "Officer",
            "STATUS": "Active",
            "PDO_CONTACT_INFO": "905-401-9618"
        },
        {
            "TOUNIQUENUMBER": "100576372",
            "TO": "Shishuai Lu",
            "Relationship Type": "Principal",
            "STATUS": "Active",
            "PDO_CONTACT_INFO": "905-324-5588"
        },
        {
            "TOUNIQUENUMBER": "100576372",
            "TO": "Shishuai Lu",
            "Relationship Type": "Director",
            "STATUS": "Active",
            "PDO_CONTACT_INFO": "905-324-5588"
        },
        {
            "TOUNIQUENUMBER": "100576372",
            "TO": "Shishuai Lu",
            "Relationship Type": "Officer",
            "STATUS": "Active",
            "PDO_CONTACT_INFO": "905-324-5588"
        }
    ],
    "builderConvictions": [],
    "builderMembers": [
        {
            "Account Number": "B47740",
            "Umbrella": null,
            "Umbrella ID": null,
            "VB_NAME": "Brighteast Inc.",
            "OPERATINGNAME": "Brighteast Construction",
            "LICENCE_STATUS": "Licensed",
            "MEMBERVBNUM": null,
            "MEMBERNAME": null,
            "MEMBEROPERATINGNAME": null,
            "MEMBERLICENCESTATUS": null
        }
    ],
    "builderCondoProjects": [],
    "builderConditions": []
}