{
    "builderSummary": [
        {
            "Account Number": "B62138",
            "Umbrella": null,
            "Umbrella ID": null,
            "VB_NAME": "N. Star Investments Inc.",
            "OPERATINGNAME": "N. Star Investments Inc.",
            "CITY": "Burlington",
            "HCRA_INITIALLICENSEDATE": "2023-05-02",
            "LICENCE_STATUS": "Licensed",
            "HCRA_LICENSERENEWEDON": "2023-05-02 17:37:31.000 +0000",
            "Expiry Date": "2024-05-03",
            "RENL_IN_PROCESS_FLAG": "N",
            "ADDRESS": "2197 Arrow Court",
            "TELEPHONE": "905-467-8707",
            "FAX": null,
            "WEBSITEURL": null,
            "EMAIL": "jadiwinata81@gmail.com",
            "ACCOUNTNUMBER": null,
            "Total Outstanding Amount": null,
            "TAB": null,
            "BREACH": null,
            "SUMM_FREEHOLD": null,
            "SUMM_CONDO": null,
            "SUMM_TOTAL": null,
            "SUMM_CC": null,
            "SUMM_MINOR": null,
            "SUMM_MINOR_AMT": null,
            "SUMM_MAJOR": null,
            "SUMM_MAJOR_AMT": null,
            "SUMM_TOTAL_CLAIMS": null
        }
    ],
    "builderPDOs": [
        {
            "TOUNIQUENUMBER": "600014147",
            "TO": "Sally Mutheardy",
            "Relationship Type": "Principal",
            "STATUS": "Active",
            "PDO_CONTACT_INFO": "289-828-8900"
        },
        {
            "TOUNIQUENUMBER": "600014148",
            "TO": "Arlene Adiwinata",
            "Relationship Type": "Principal",
            "STATUS": "Active",
            "PDO_CONTACT_INFO": "905-467-0367"
        },
        {
            "TOUNIQUENUMBER": "600013906",
            "TO": "John Adiwinata",
            "Relationship Type": "Principal",
            "STATUS": "Active",
            "PDO_CONTACT_INFO": "905-467-8707"
        },
        {
            "TOUNIQUENUMBER": "600013906",
            "TO": "John Adiwinata",
            "Relationship Type": "Director",
            "STATUS": "Active",
            "PDO_CONTACT_INFO": "905-467-8707"
        },
        {
            "TOUNIQUENUMBER": "600013906",
            "TO": "John Adiwinata",
            "Relationship Type": "Officer",
            "STATUS": "Active",
            "PDO_CONTACT_INFO": "905-467-8707"
        }
    ],
    "builderConvictions": [],
    "builderMembers": [
        {
            "Account Number": "B62138",
            "Umbrella": null,
            "Umbrella ID": null,
            "VB_NAME": "N. Star Investments Inc.",
            "OPERATINGNAME": "N. Star Investments Inc.",
            "LICENCE_STATUS": "Licensed",
            "MEMBERVBNUM": null,
            "MEMBERNAME": null,
            "MEMBEROPERATINGNAME": null,
            "MEMBERLICENCESTATUS": null
        }
    ],
    "builderCondoProjects": [],
    "builderConditions": []
}